README.md
setup.cfg
setup.py
csrgraph/__init__.py
csrgraph/ggvec.py
csrgraph/glove.py
csrgraph/graph.py
csrgraph/grarep.py
csrgraph/methods.py
csrgraph/random_walks.py
csrgraph/version.py
csrgraph.egg-info/PKG-INFO
csrgraph.egg-info/SOURCES.txt
csrgraph.egg-info/dependency_links.txt
csrgraph.egg-info/requires.txt
csrgraph.egg-info/top_level.txt