Metadata-Version: 1.0
Name: csrgraph
Version: 0.1.20
Summary: Fast python graphs
Home-page: https://github.com/VHRanger/CSRGraph
Author: Matt Ranger
Author-email: UNKNOWN
License: MIT
Keywords: graph,network
Platform: UNKNOWN
